hydromt_wflow/__init__.py
hydromt_wflow/naming.py
hydromt_wflow/utils.py
hydromt_wflow/version.py
hydromt_wflow/version_upgrade.py
hydromt_wflow/wflow_base.py
hydromt_wflow/wflow_sbm.py
hydromt_wflow/wflow_sediment.py
hydromt_wflow/components/__init__.py
hydromt_wflow/components/config.py
hydromt_wflow/components/forcing.py
hydromt_wflow/components/geoms.py
hydromt_wflow/components/output_csv.py
hydromt_wflow/components/output_grid.py
hydromt_wflow/components/output_scalar.py
hydromt_wflow/components/states.py
hydromt_wflow/components/staticmaps.py
hydromt_wflow/components/tables.py
hydromt_wflow/components/utils.py
hydromt_wflow/data/default_config_headers.toml
hydromt_wflow/data/parameters_data.yml
hydromt_wflow/data/lulc/v0.8/corine_mapping.csv
hydromt_wflow/data/lulc/v0.8/esa_worldcover_mapping.csv
hydromt_wflow/data/lulc/v0.8/glcnmo_mapping.csv
hydromt_wflow/data/lulc/v0.8/globcover_mapping.csv
hydromt_wflow/data/lulc/v0.8/paddy_mapping.csv
hydromt_wflow/data/lulc/v0.8/vito_mapping.csv
hydromt_wflow/data/lulc/v1.0/corine_mapping.csv
hydromt_wflow/data/lulc/v1.0/esa_worldcover_mapping.csv
hydromt_wflow/data/lulc/v1.0/glcnmo_mapping.csv
hydromt_wflow/data/lulc/v1.0/globcover_mapping.csv
hydromt_wflow/data/lulc/v1.0/paddy_mapping.csv
hydromt_wflow/data/lulc/v1.0/vito_mapping.csv
hydromt_wflow/data/rivwth/koppen_geiger.csv
hydromt_wflow/data/rivwth/regr_chelsa.csv
hydromt_wflow/data/wflow_sbm/river_manning_mapping.csv
hydromt_wflow/data/wflow_sbm/wflow_sbm.toml
hydromt_wflow/data/wflow_sediment/riverbedsed_mapping.csv
hydromt_wflow/data/wflow_sediment/wflow_sediment.toml
hydromt_wflow/workflows/__init__.py
hydromt_wflow/workflows/basemaps.py
hydromt_wflow/workflows/connect.py
hydromt_wflow/workflows/demand.py
hydromt_wflow/workflows/forcing.py
hydromt_wflow/workflows/gauges.py
hydromt_wflow/workflows/glaciers.py
hydromt_wflow/workflows/landuse.py
hydromt_wflow/workflows/ptf.py
hydromt_wflow/workflows/reservoirs.py
hydromt_wflow/workflows/river.py
hydromt_wflow-1.0.1.dist-info/licenses/LICENSE
hydromt_wflow-1.0.1.dist-info/METADATA
hydromt_wflow-1.0.1.dist-info/WHEEL
hydromt_wflow-1.0.1.dist-info/entry_points.txt
hydromt_wflow-1.0.1.dist-info/top_level.txt
hydromt_wflow-1.0.1.dist-info/RECORD
