Metadata-Version: 2.4
Name: hydromt_wflow
Version: 1.0.1
Summary: HydroMT plugin for wflow.
Author-email: Dirk Eilander <dirk.eilander@deltares.nl>, Hélène Boisgontier <helene.boisgontier@deltares.nl>, Joost Buitink <joost.buitink@deltares.nl>, Brendan Dalmijn <brendan.dalmijn@deltares.nl>, Tjalling de Jong <tjalling.dejong@deltares.nl>, Sam Vente <sam.vente@deltares.nl>, Marnix Kraus <marnix.kraus@deltares.nl>, Luuk Blom <luuk.blom@deltares.nl>
License-Expression: GPL-3.0-or-later
Project-URL: Documentation, http://deltares.github.io/hydromt_wflow/latest/
Project-URL: Source, https://github.com/Deltares/hydromt_wflow
Classifier: Development Status :: 4 - Beta
Classifier: Intended Audience :: Developers
Classifier: Intended Audience :: Science/Research
Classifier: Topic :: Scientific/Engineering :: Hydrology
Classifier: Programming Language :: Python :: 3
Requires-Python: >=3.11
License-File: LICENSE
Requires-Dist: dask
Requires-Dist: geopandas>=0.10
Requires-Dist: hydromt>=1.3.0
Requires-Dist: numpy
Requires-Dist: rasterio<1.5
Requires-Dist: pandas
Requires-Dist: pyflwdir>=0.5.7
Requires-Dist: pyproj
Requires-Dist: scipy
Requires-Dist: shapely
Requires-Dist: xarray
Requires-Dist: pooch
Provides-Extra: dist
Requires-Dist: build; extra == "dist"
Requires-Dist: twine; extra == "dist"
Provides-Extra: lint
Requires-Dist: pre-commit; extra == "lint"
Requires-Dist: ruff; extra == "lint"
Provides-Extra: docs
Requires-Dist: nbsphinx; extra == "docs"
Requires-Dist: pydata-sphinx-theme; extra == "docs"
Requires-Dist: sphinx; extra == "docs"
Requires-Dist: sphinx_design; extra == "docs"
Requires-Dist: sphinx_autosummary_accessors; extra == "docs"
Requires-Dist: sbom4python; extra == "docs"
Provides-Extra: examples
Requires-Dist: cartopy; extra == "examples"
Requires-Dist: jupyterlab; extra == "examples"
Requires-Dist: nbconvert; extra == "examples"
Requires-Dist: notebook; extra == "examples"
Provides-Extra: extra
Requires-Dist: gwwapi; extra == "extra"
Requires-Dist: hydroengine; extra == "extra"
Requires-Dist: pyet; extra == "extra"
Requires-Dist: wradlib; extra == "extra"
Provides-Extra: test
Requires-Dist: pytest>=2.7.3; extra == "test"
Requires-Dist: pytest-cov; extra == "test"
Requires-Dist: pytest-mock; extra == "test"
Requires-Dist: pytest-timeout; extra == "test"
Requires-Dist: pytest-benchmark; extra == "test"
Provides-Extra: full
Requires-Dist: hydromt_wflow[examples,extra]; extra == "full"
Provides-Extra: dev
Requires-Dist: hydromt_wflow[dist,docs,lint,test]; extra == "dev"
Provides-Extra: all
Requires-Dist: hydromt_wflow[dev,full]; extra == "all"
Dynamic: license-file
